[
  {
    "title": "Pulp Fiction",
    "rank": 0,
    "id": "tt0110912"
  },
  {
    "title": "The Prestige",
    "rank": 0,
    "id": "tt0482571"
  },
  {
    "title": "The Lord of the Rings: The Return of the King",
    "rank": 0,
    "id": "tt0167260"
  },
  {
    "title": "12 Angry Men",
    "rank": 0,
    "id": "tt0050083"
  },
  {
    "title": "Saving Private Ryan",
    "rank": 0,
    "id": "tt0120815"
  },
  {
    "title": "The Good, the Bad and the Ugly",
    "rank": 0,
    "id": "tt0060196"
  },
  {
    "title": "The Great Dictator",
    "rank": 0,
    "id": "tt0032553"
  },
  {
    "title": "The Lion King",
    "rank": 0,
    "id": "tt0110357"
  },
  {
    "title": "Braveheart",
    "rank": 0,
    "id": "tt0112573"
  },
  {
    "title": "Dr. Strangelove or: How I Learned to Stop Worrying and Love the Bomb",
    "rank": 0,
    "id": "tt0057012"
  },
  {
    "title": "Schindler's List",
    "rank": 0,
    "id": "tt0108052"
  },
  {
    "title": "Full Metal Jacket",
    "rank": 0,
    "id": "tt0093058"
  },
  {
    "title": "Once Upon a Time in the West",
    "rank": 0,
    "id": "tt0064116"
  },
  {
    "title": "Rashomon",
    "rank": 0,
    "id": "tt0042876"
  },
  {
    "title": "Metropolis",
    "rank": 0,
    "id": "tt0017136"
  }
]